{
  "generatedAtUtc": "2026-03-16T01:48:04.452295Z",
  "repoRoot": "F:\\repos\\comsect1-architecture",
  "stages": [
    {
      "name": "meta-advisory",
      "status": "clean",
      "exitCode": 0,
      "note": "No spec modifications detected",
      "outputPath": null
    },
    {
      "name": "spec",
      "status": "passed",
      "exitCode": 0,
      "note": "Verify-Spec passed",
      "outputPath": null
    },
    {
      "name": "tooling",
      "status": "passed",
      "exitCode": 0,
      "note": "Verify-ToolingConsistency passed",
      "outputPath": null
    },
    {
      "name": "code",
      "status": "skipped",
      "exitCode": 0,
      "note": "Skipped by flag",
      "outputPath": null
    },
    {
      "name": "oop",
      "status": "skipped",
      "exitCode": 0,
      "note": "OOP root not provided/found; skipped OOP stage",
      "outputPath": null
    }
  ],
  "gatePassed": true
}